README
setup.py
diffval/__init__.py
diffval/idlval.py
diffval/interface.py
diffval/log.py
diffval/pyval.py
diffval/session.py
diffval/test.py
diffval.egg-info/PKG-INFO
diffval.egg-info/SOURCES.txt
diffval.egg-info/dependency_links.txt
diffval.egg-info/entry_points.txt
diffval.egg-info/top_level.txt