Metadata-Version: 1.0
Name: diffval
Version: 0.11
Summary: Validates tests by comparing real output against expected output
Home-page: http://efw.ssl.berkeley.edu/packages/diffval
Author: Matt Born
Author-email: mattborn@ssl.berkeley.edu
License: UNKNOWN
Platform: UNKNOWN
Classifier: Development Status :: 3 - Alpha
Classifier: Intended Audience :: Developers
Classifier: License :: OSI Approved :: Apache Software License
Classifier: Topic :: Software Development :: Testing
